{
  "元旦节": "01-01",
  "情人节": "02-14",
  "妇女节": "03-08",
  "植树节": "03-12",
  "劳动节": "05-01",
  "青年节": "05-04",
  "母亲节": "05-11",
  "儿童节": "06-01",
  "建党节": "07-01",
  "航海日节": "07-11",
  "建军节": "08-01",
  "教师节": "09-10",
  "国庆节": "10-01",
  "记者节": "11-08",
  "光棍节": "11-11",
  "圣诞节": "12-25",
  "立春": "02-04",
  "雨水": "02-19",
  "惊蛰": "03-05",
  "春分": "03-20",
  "愚人节": "04-01",
  "清明": "04-04",
  "谷雨": "04-19",
  "立夏": "05-05",
  "小满": "05-20",
  "芒种": "06-05",
  "夏至": "06-21",
  "小暑": "07-06",
  "大暑": "07-22",
  "立秋": "08-07",
  "处暑": "08-22",
  "白露": "09-07",
  "秋分": "09-22",
  "寒露": "10-08",
  "霜降": "10-23",
  "立冬": "11-07",
  "小雪": "11-22",
  "大雪": "12-07",
  "冬至": "12-21",
  "小寒": "01-06",
  "大寒": "01-20",
  "7夕": "",
  "春节": "",
  "中秋节": "",
  "端午节": "",
  "父亲节": ""


}